usecortex_ai/__init__.py
usecortex_ai/client.py
usecortex_ai/environment.py
usecortex_ai/raw_client.py
usecortex_ai/core/__init__.py
usecortex_ai/core/api_error.py
usecortex_ai/core/client_wrapper.py
usecortex_ai/core/datetime_utils.py
usecortex_ai/core/file.py
usecortex_ai/core/force_multipart.py
usecortex_ai/core/http_client.py
usecortex_ai/core/http_response.py
usecortex_ai/core/jsonable_encoder.py
usecortex_ai/core/pydantic_utilities.py
usecortex_ai/core/query_encoder.py
usecortex_ai/core/remove_none_from_dict.py
usecortex_ai/core/request_options.py
usecortex_ai/core/serialization.py
usecortex_ai/document/__init__.py
usecortex_ai/document/client.py
usecortex_ai/document/raw_client.py
usecortex_ai/embeddings/__init__.py
usecortex_ai/embeddings/client.py
usecortex_ai/embeddings/raw_client.py
usecortex_ai/errors/__init__.py
usecortex_ai/errors/bad_request_error.py
usecortex_ai/errors/forbidden_error.py
usecortex_ai/errors/internal_server_error.py
usecortex_ai/errors/not_found_error.py
usecortex_ai/errors/service_unavailable_error.py
usecortex_ai/errors/unauthorized_error.py
usecortex_ai/errors/unprocessable_entity_error.py
usecortex_ai/fetch/__init__.py
usecortex_ai/fetch/client.py
usecortex_ai/fetch/raw_client.py
usecortex_ai/search/__init__.py
usecortex_ai/search/client.py
usecortex_ai/search/raw_client.py
usecortex_ai/search/types/__init__.py
usecortex_ai/search/types/alpha.py
usecortex_ai/sources/__init__.py
usecortex_ai/sources/client.py
usecortex_ai/sources/raw_client.py
usecortex_ai/tenant/__init__.py
usecortex_ai/tenant/client.py
usecortex_ai/tenant/raw_client.py
usecortex_ai/types/__init__.py
usecortex_ai/types/actual_error_response.py
usecortex_ai/types/add_user_memory_response.py
usecortex_ai/types/app_sources_upload_data.py
usecortex_ai/types/attachment_model.py
usecortex_ai/types/batch_upload_data.py
usecortex_ai/types/bm_25_operator_type.py
usecortex_ai/types/body_scrape_webpage_upload_scrape_webpage_post.py
usecortex_ai-0.3.5.dist-info/licenses/LICENSE
usecortex_ai-0.3.5.dist-info/METADATA
usecortex_ai-0.3.5.dist-info/WHEEL
usecortex_ai-0.3.5.dist-info/top_level.txt
usecortex_ai-0.3.5.dist-info/RECORD
