Metadata-Version: 2.4
Name: usecortex-ai
Version: 0.3.5
Summary: The official Python SDK for the Cortex AI platform.
Author-email: Nishkarsh Shrivastava <nishkarsh@usecortex.ai>
License: Copyright (c) 2024 Cortex AI
Project-URL: Homepage, https://www.usecortex.ai/
Project-URL: Documentation, https://docs.usecortex.ai/
Keywords: cortex,ai,sdk,api,generative ai,rag
Classifier: Development Status :: 5 - Production/Stable
Classifier: Programming Language :: Python :: 3
Classifier: Programming Language :: Python :: 3.10
Classifier: Programming Language :: Python :: 3.11
Classifier: Programming Language :: Python :: 3.12
Classifier: Intended Audience :: Developers
Classifier: Topic :: Software Development :: Libraries :: Python Modules
Classifier: Typing :: Typed
Requires-Python: >=3.10
License-File: LICENSE
Requires-Dist: httpx>=0.24
Requires-Dist: pydantic<3,>=1.10
Dynamic: license-file
